<?xml version="1.0" encoding="UTF-8"?>
<tour apprev="17336" start="node1" appversion="6.0.6">
  <panorama id="node1">
    <input width="320" levelbias="0.400" overlap="1" height="320" levelingpitch="0" leveltileurl="tiles/node1/cf_%c/l_%l/c_%x/tile_%y.jpg" leveltilesize="510" levelbiashidpi="1.000" levelingroll="0">
      <level preload="1" width="320" predecode="1" height="320"/>
      <preview strip="1" color="0x808080"/>
    </input>
    <view pannorth="0" fovmode="0">
      <start tilt="0" pan="0" projection="4" fov="70"/>
      <flyin tilt="-90" pan="0" projection="9" fov="170"/>
      <min fovpixel="2" tilt="-90" pan="0"/>
      <max tilt="90" pan="360" scaletofit="1" fov="120" fovfisheye="360" fovstereographic="270"/>
    </view>
    <userdata copyright="" info="" tags="" author="" customnodeid="" description="" latitude="" title="" source="" datetime="" longitude="" comment=""/>
    <hotspots wordwrap="1" width="180" height="20">
      <label background="1" wordwrap="1" enabled="0" backgroundalpha="1" textcolor="0x000000" width="180" borderradius="1" backgroundcolor="0xffffff" bordercolor="0x000000" border="1" height="20" borderalpha="1" textalpha="1"/>
      <polystyle backgroundalpha="0.25098" handcursor="1" backgroundcolor="0xff0648" bordercolor="0xff0004" borderalpha="1" mode="1"/>
      <hotspot url="{node2}" tilt="-19.15" pan="-89.71" description="前厅" id="Point02" title="" skinid="Hotspot 4" target="0.0/0.0/70.0"/>
    </hotspots>
    <media/>
    <transition zoomfov="20" enabled="1" zoomout="0" zoomoutpause="1" softedge="0" type="diptocolor" blendtime="1" zoomin="0" blendcolor="0x000000" zoomspeed="2"/>
    <animation animsequence="Animation01" useinautorotation="0" syncanimationwithvideo="0"/>
    <control rubberband="0" lockedkeyboardzoom="0" sensitivity="8" speedwheel="1" lockedmouse="0" dblclickfullscreen="0" lockedwheel="0" invertcontrol="1" contextprojections="0" lockedkeyboard="0" contextfullscreen="1" simulatemass="1" hideabout="0" invertwheel="0"/>
  </panorama>
  <panorama id="node2">
    <input width="320" levelbias="0.400" overlap="1" height="320" levelingpitch="0" leveltileurl="tiles/node2/cf_%c/l_%l/c_%x/tile_%y.jpg" leveltilesize="510" levelbiashidpi="1.000" levelingroll="0">
      <level preload="1" width="320" predecode="1" height="320"/>
      <preview strip="1" color="0x808080"/>
    </input>
    <view pannorth="0" fovmode="0">
      <start tilt="0" pan="0" projection="4" fov="70"/>
      <flyin tilt="-90" pan="0" projection="9" fov="170"/>
      <min fovpixel="2" tilt="-90" pan="0"/>
      <max tilt="90" pan="360" scaletofit="1" fov="120" fovfisheye="360" fovstereographic="270"/>
    </view>
    <userdata copyright="" info="" tags="QUANJING" author="" customnodeid="" description="" latitude="" title="" source="" datetime="" longitude="" comment=""/>
    <hotspots wordwrap="1" width="180" height="20">
      <label background="1" wordwrap="1" enabled="0" backgroundalpha="1" textcolor="0x000000" width="180" borderradius="1" backgroundcolor="0xffffff" bordercolor="0x000000" border="1" height="20" borderalpha="1" textalpha="1"/>
      <polystyle backgroundalpha="0.25098" handcursor="1" backgroundcolor="0xff0648" bordercolor="0xff0004" borderalpha="1" mode="1"/>
      <hotspot url="{node1}" tilt="-31.52" pan="-86.66" description="" id="Point01" title="" skinid="Hotspot 4" target="-88.6/9.5/45.0"/>
      <hotspot url="{node3}" tilt="-39.82" pan="-269.81" description="" id="Point02" title="" skinid="Hotspot 4" target="88.9/1.5/45.0"/>
      <hotspot url="{node4}" tilt="-41.75" pan="359.18" description="" id="Point03" title="" skinid="Hotspot 4" target="0.0/0.0/70.0"/>
      <hotspot url="{node5}" tilt="-37.07" pan="-178.97" description="" id="Point04" title="" skinid="Hotspot 4" target="-179.7/4.2/45.0"/>
    </hotspots>
    <media/>
    <transition zoomfov="20" enabled="1" zoomout="0" zoomoutpause="1" softedge="0" type="diptocolor" blendtime="1" zoomin="0" blendcolor="0x000000" zoomspeed="2"/>
    <animation animsequence="Animation01" useinautorotation="0" syncanimationwithvideo="0"/>
    <control rubberband="0" lockedkeyboardzoom="0" sensitivity="8" speedwheel="1" lockedmouse="0" dblclickfullscreen="0" lockedwheel="0" invertcontrol="1" contextprojections="0" lockedkeyboard="0" contextfullscreen="1" simulatemass="1" hideabout="0" invertwheel="0"/>
  </panorama>
  <panorama id="node3">
    <input width="320" levelbias="0.400" overlap="1" height="320" levelingpitch="0" leveltileurl="tiles/node3/cf_%c/l_%l/c_%x/tile_%y.jpg" leveltilesize="510" levelbiashidpi="1.000" levelingroll="0">
      <level preload="1" width="320" predecode="1" height="320"/>
      <preview strip="1" color="0x808080"/>
    </input>
    <view pannorth="0" fovmode="0">
      <start tilt="0" pan="0" projection="4" fov="70"/>
      <flyin tilt="-90" pan="0" projection="9" fov="170"/>
      <min fovpixel="2" tilt="-90" pan="0"/>
      <max tilt="90" pan="360" scaletofit="1" fov="120" fovfisheye="360" fovstereographic="270"/>
    </view>
    <userdata copyright="" info="" tags="QUANJING" author="" customnodeid="" description="" latitude="" title="" source="" datetime="" longitude="" comment=""/>
    <hotspots wordwrap="1" width="180" height="20">
      <label background="1" wordwrap="1" enabled="0" backgroundalpha="1" textcolor="0x000000" width="180" borderradius="1" backgroundcolor="0xffffff" bordercolor="0x000000" border="1" height="20" borderalpha="1" textalpha="1"/>
      <polystyle backgroundalpha="0.25098" handcursor="1" backgroundcolor="0xff0648" bordercolor="0xff0004" borderalpha="1" mode="1"/>
    </hotspots>
    <media/>
    <transition zoomfov="20" enabled="1" zoomout="0" zoomoutpause="1" softedge="0" type="diptocolor" blendtime="1" zoomin="0" blendcolor="0x000000" zoomspeed="2"/>
    <animation animsequence="Animation01" useinautorotation="0" syncanimationwithvideo="0"/>
    <control rubberband="0" lockedkeyboardzoom="0" sensitivity="8" speedwheel="1" lockedmouse="0" dblclickfullscreen="0" lockedwheel="0" invertcontrol="1" contextprojections="0" lockedkeyboard="0" contextfullscreen="1" simulatemass="1" hideabout="0" invertwheel="0"/>
  </panorama>
  <panorama id="node4">
    <input width="320" levelbias="0.400" overlap="1" height="320" levelingpitch="0" leveltileurl="tiles/node4/cf_%c/l_%l/c_%x/tile_%y.jpg" leveltilesize="510" levelbiashidpi="1.000" levelingroll="0">
      <level preload="1" width="320" predecode="1" height="320"/>
      <preview strip="1" color="0x808080"/>
    </input>
    <view pannorth="0" fovmode="0">
      <start tilt="0" pan="0" projection="4" fov="70"/>
      <flyin tilt="-90" pan="0" projection="9" fov="170"/>
      <min fovpixel="2" tilt="-90" pan="0"/>
      <max tilt="90" pan="360" scaletofit="1" fov="120" fovfisheye="360" fovstereographic="270"/>
    </view>
    <userdata copyright="" info="" tags="QUANJING" author="" customnodeid="" description="" latitude="" title="" source="" datetime="" longitude="" comment=""/>
    <hotspots wordwrap="1" width="180" height="20">
      <label background="1" wordwrap="1" enabled="0" backgroundalpha="1" textcolor="0x000000" width="180" borderradius="1" backgroundcolor="0xffffff" bordercolor="0x000000" border="1" height="20" borderalpha="1" textalpha="1"/>
      <polystyle backgroundalpha="0.25098" handcursor="1" backgroundcolor="0xff0648" bordercolor="0xff0004" borderalpha="1" mode="1"/>
    </hotspots>
    <media/>
    <transition zoomfov="20" enabled="1" zoomout="0" zoomoutpause="1" softedge="0" type="diptocolor" blendtime="1" zoomin="0" blendcolor="0x000000" zoomspeed="2"/>
    <animation animsequence="Animation01" useinautorotation="0" syncanimationwithvideo="0"/>
    <control rubberband="0" lockedkeyboardzoom="0" sensitivity="8" speedwheel="1" lockedmouse="0" dblclickfullscreen="0" lockedwheel="0" invertcontrol="1" contextprojections="0" lockedkeyboard="0" contextfullscreen="1" simulatemass="1" hideabout="0" invertwheel="0"/>
  </panorama>
  <panorama id="node5">
    <input width="320" levelbias="0.400" overlap="1" height="320" levelingpitch="0" leveltileurl="tiles/node5/cf_%c/l_%l/c_%x/tile_%y.jpg" leveltilesize="510" levelbiashidpi="1.000" levelingroll="0">
      <level preload="1" width="320" predecode="1" height="320"/>
      <preview strip="1" color="0x808080"/>
    </input>
    <view pannorth="0" fovmode="0">
      <start tilt="0" pan="0" projection="4" fov="70"/>
      <flyin tilt="-90" pan="0" projection="9" fov="170"/>
      <min fovpixel="2" tilt="-90" pan="0"/>
      <max tilt="90" pan="360" scaletofit="1" fov="120" fovfisheye="360" fovstereographic="270"/>
    </view>
    <userdata copyright="" info="" tags="QUANJING" author="" customnodeid="" description="" latitude="" title="" source="" datetime="" longitude="" comment=""/>
    <hotspots wordwrap="1" width="180" height="20">
      <label background="1" wordwrap="1" enabled="0" backgroundalpha="1" textcolor="0x000000" width="180" borderradius="1" backgroundcolor="0xffffff" bordercolor="0x000000" border="1" height="20" borderalpha="1" textalpha="1"/>
      <polystyle backgroundalpha="0.25098" handcursor="1" backgroundcolor="0xff0648" bordercolor="0xff0004" borderalpha="1" mode="1"/>
    </hotspots>
    <media/>
    <transition zoomfov="20" enabled="1" zoomout="0" zoomoutpause="1" softedge="0" type="diptocolor" blendtime="1" zoomin="0" blendcolor="0x000000" zoomspeed="2"/>
    <animation animsequence="Animation01" useinautorotation="0" syncanimationwithvideo="0"/>
    <control rubberband="0" lockedkeyboardzoom="0" sensitivity="8" speedwheel="1" lockedmouse="0" dblclickfullscreen="0" lockedwheel="0" invertcontrol="1" contextprojections="0" lockedkeyboard="0" contextfullscreen="1" simulatemass="1" hideabout="0" invertwheel="0"/>
  </panorama>
  <masternode>
    <userdata copyright="" info="" tags="" author="" customnodeid="" description="" latitude="" title="" source="" datetime="" longitude="" comment=""/>
  </masternode>
</tour>
